MANIFEST.in
README.rst
setup.cfg
setup.py
lib/esa.hxx
lib/esary.cpp
lib/esary.hpp
lib/sais.hxx
pykwic.egg-info/PKG-INFO
pykwic.egg-info/SOURCES.txt
pykwic.egg-info/dependency_links.txt
pykwic.egg-info/requires.txt
pykwic.egg-info/top_level.txt
src/esary.pxd
src/pykwic.cpp
src/pykwic.pyx