Metadata-Version: 1.1
Name: pykwic
Version: 0.1.4
Summary: KWIC Library for unicode text using Suffix Array.
Home-page: https://github.com/shunsukeaihara/pykwic
Author: Shunsuke Aihara
Author-email: UNKNOWN
License: MIT License
Platform: UNKNOWN
Classifier: Programming Language :: Python :: 3
Classifier: Programming Language :: Python :: 2
